pyArango/__init__.py
pyArango/action.py
pyArango/admin.py
pyArango/ca_certificate.py
pyArango/collection.py
pyArango/connection.py
pyArango/consts.py
pyArango/database.py
pyArango/document.py
pyArango/foxx.py
pyArango/gevent_session.py
pyArango/graph.py
pyArango/index.py
pyArango/jwauth.py
pyArango/query.py
pyArango/tasks.py
pyArango/theExceptions.py
pyArango/users.py
pyArango/validation.py
pyArango/tests/__init__.py
pyArango/tests/doc_save_benchmark.py
pyArango/tests/doc_save_bulk_benchmark.py
pyArango/tests/tests.py
pyArango/tests/validators_tests.py
pyArango-2.0.2.dist-info/LICENSE
pyArango-2.0.2.dist-info/METADATA
pyArango-2.0.2.dist-info/WHEEL
pyArango-2.0.2.dist-info/entry_points.txt
pyArango-2.0.2.dist-info/top_level.txt
pyArango-2.0.2.dist-info/RECORD
