Metadata-Version: 1.1
Name: pyArango
Version: 2.0.2
Summary: An easy to use python driver for ArangoDB with built-in validation
Home-page: https://github.com/tariqdaouda/pyArango
Author: Tariq Daouda
Author-email: tariq.daouda@umontreal.ca
License: ApacheV2
Keywords: database ORM nosql arangodb driver validation
Platform: UNKNOWN
Classifier: Development Status :: 5 - Production/Stable
Classifier: Intended Audience :: Developers
Classifier: Intended Audience :: System Administrators
Classifier: Topic :: Software Development :: Libraries
Classifier: Topic :: Database
Classifier: Topic :: Database :: Database Engines/Servers
Classifier: License :: OSI Approved :: Apache Software License
Classifier: Programming Language :: Python :: 2.7
Classifier: Programming Language :: Python :: 3
